calmacentral/Calculadora.py
calmacentral/__init__.py
calmacentral-0.0.1.dist-info/LICENSE
calmacentral-0.0.1.dist-info/METADATA
calmacentral-0.0.1.dist-info/WHEEL
calmacentral-0.0.1.dist-info/top_level.txt
calmacentral-0.0.1.dist-info/RECORD
